spegel/__init__.py
spegel/__main__.py
spegel/config.py
spegel/llm.py
spegel/main.py
spegel/views.py
spegel/web.py
spegel-0.1.3.dist-info/METADATA
spegel-0.1.3.dist-info/WHEEL
spegel-0.1.3.dist-info/entry_points.txt
spegel-0.1.3.dist-info/licenses/LICENSE
spegel-0.1.3.dist-info/RECORD
