Metadata-Version: 2.4
Name: spegel
Version: 0.1.3
Summary: Spegel - Reflect the web through AI. A terminal browser with multiple AI-powered views.
Project-URL: Homepage, https://github.com/simedw/spegel
Project-URL: Repository, https://github.com/simedw/spegel
Project-URL: Bug Tracker, https://github.com/simedw/spegel/issues
Project-URL: Documentation, https://github.com/simedw/spegel#readme
Author-email: Simon Edwardsson <simon.edwardsson@gmail.com>
License-Expression: MIT
License-File: LICENSE
Keywords: ai,browser,llm,terminal,textual,tui,web
Classifier: Development Status :: 3 - Alpha
Classifier: Environment :: Console
Classifier: Intended Audience :: Developers
Classifier: Intended Audience :: End Users/Desktop
Classifier: License :: OSI Approved :: MIT License
Classifier: Operating System :: OS Independent
Classifier: Programming Language :: Python :: 3
Classifier: Programming Language :: Python :: 3.11
Classifier: Programming Language :: Python :: 3.12
Classifier: Programming Language :: Python :: 3.13
Classifier: Topic :: Internet :: WWW/HTTP :: Browsers
Classifier: Topic :: Software Development :: Libraries :: Python Modules
Classifier: Topic :: Terminals
Classifier: Topic :: Text Processing :: Markup :: HTML
Requires-Python: >=3.11
Requires-Dist: beautifulsoup4>=4.13.4
Requires-Dist: html2text>=2025.4.15
Requires-Dist: litellm>=1.54.0
Requires-Dist: lxml>=5.4.0
Requires-Dist: pydantic>=2.7.1
Requires-Dist: python-dotenv>=1.1.0
Requires-Dist: requests>=2.32.4
Requires-Dist: textual>=3.3.0
Provides-Extra: dev
Requires-Dist: pytest-asyncio>=0.21.0; extra == 'dev'
Requires-Dist: pytest>=7.0.0; extra == 'dev'
Requires-Dist: ruff>=0.8.0; extra == 'dev'
